polars_scheduler-0.2.0.dist-info/METADATA
polars_scheduler-0.2.0.dist-info/WHEEL
polars_scheduler/__init__.py
polars_scheduler/utils.py
polars_scheduler/_polars_scheduler.abi3.so
polars_scheduler-0.2.0.dist-info/RECORD
