Metadata-Version: 2.4
Name: polars-scheduler
Version: 0.2.0
Classifier: Development Status :: 4 - Beta
Classifier: Intended Audience :: Developers
Classifier: Natural Language :: English
Classifier: License :: OSI Approved :: MIT License
Classifier: Operating System :: OS Independent
Classifier: Programming Language :: Python
Classifier: Programming Language :: Python :: Implementation :: CPython
Classifier: Programming Language :: Python :: 3
Classifier: Programming Language :: Python :: 3.9
Classifier: Programming Language :: Python :: 3.10
Classifier: Programming Language :: Python :: 3.11
Classifier: Programming Language :: Python :: 3.12
Classifier: Programming Language :: Python :: 3.13
Requires-Dist: polars>=1.21.0 ; extra == 'polars'
Requires-Dist: polars-lts-cpu>=1.21.0 ; extra == 'polars-lts-cpu'
Requires-Dist: pdm-bump>=0.9.10 ; extra == 'dev'
Requires-Dist: pdm>=2.22.3 ; extra == 'dev'
Requires-Dist: pre-commit>=4.1.0 ; extra == 'dev'
Requires-Dist: pytest>=8.3.4 ; extra == 'dev'
Provides-Extra: polars
Provides-Extra: polars-lts-cpu
Provides-Extra: dev
Summary: A Polars plugin for easily scheduling recurring events with constraints.
Author: Louis Maddox <louismmx@gmail.com>
Author-email: Louis Maddox <louismmx@gmail.com>
License: MIT
Requires-Python: >=3.9
Project-URL: Homepage, https://github.com/lmmx/polars-scheduler
Project-URL: Repository, https://github.com/lmmx/polars-scheduler.git
